xsql/__init__.py
xsql/_core.cpp
xsql/_core.cpython-39-x86_64-linux-gnu.so
xsql/_loader.py
xsql/_security.py
xsql/_summary.py
xsql/_types.py
pyxsql-1.2.0.dist-info/METADATA
pyxsql-1.2.0.dist-info/WHEEL
pyxsql-1.2.0.dist-info/top_level.txt
pyxsql-1.2.0.dist-info/RECORD
pyxsql-1.2.0.dist-info/licenses/LICENSE
