Metadata-Version: 2.4
Name: pyxsql
Version: 1.2.0
Summary: SQL-style querying for static HTML with a deterministic node model.
Author: BORANN CHANRATHNAK
License:                                  Apache License
Classifier: Programming Language :: Python :: 3
Classifier: Programming Language :: C++
Classifier: License :: OSI Approved :: Apache Software License
Classifier: Operating System :: OS Independent
Requires-Python: >=3.9
License-File: LICENSE
Provides-Extra: test
Requires-Dist: pytest>=7.4.0; extra == "test"
Dynamic: license-file
